{
  "short_term": {
    "name": "短线交易",
    "description": "15m/30m 优先，追求当日或1-3天波动，信号确认更快，止损更紧。",
    "rules": [
      "更重视15m触发与30m方向一致性，优先做突破回踩与动量延续。",
      "止损偏紧，通常放在最近结构位之外0.5~1.0倍ATR范围。",
      "达到首个目标位后优先减仓并把止损上移至保本。"
    ]
  },
  "swing": {
    "name": "波段交易",
    "description": "30m/1h 优先，持仓周期3-10天，强调趋势段完整性。",
    "rules": [
      "更关注MA20/MA40趋势斜率与MACD零轴上下的持续性。",
      "入场以0.382/0.5回调共振为主，止损放在关键支撑/压力外侧。",
      "采用分批止盈：0.618先减仓，1.0或1.618时间窗附近再评估清仓。"
    ]
  },
  "long_term": {
    "name": "长线交易",
    "description": "以更大级别趋势为主，容忍回撤，追求趋势主升/主跌段。",
    "rules": [
      "优先服从大级别方向，短周期逆势信号仅用于减仓与风控，不轻易反手。",
      "止损与仓位更保守，避免频繁交易，强调持仓稳定性。",
      "只在关键趋势失效或时间窗衰竭时明显减仓/清仓。"
    ]
  }
}
